Metadata-Version: 2.1
Name: evepy
Version: 3.1
Summary: Simple lightweight data-interchange format, written in Python
Home-page: https://github.com/Dmunch04/EVEPY
Author: Munchii
Author-email: contact@munchii.me
License: MIT
Keywords: simple data interchange format python
Platform: UNKNOWN
Classifier: Development Status :: 4 - Beta
Classifier: Intended Audience :: End Users/Desktop
Classifier: Intended Audience :: Developers
Classifier: License :: OSI Approved :: MIT License
Classifier: Programming Language :: Python :: 2
Classifier: Programming Language :: Python :: 3
Classifier: Operating System :: OS Independent
